sitsoDB/__init__.py
sitsoDB/main.py
sitsoDB/seriesDB.csv
sitsoDB/shelfDB.csv
sitsoDB/standardDB.csv
sitsoDB-0.0.3.1.dist-info/LICENSE
sitsoDB-0.0.3.1.dist-info/METADATA
sitsoDB-0.0.3.1.dist-info/WHEEL
sitsoDB-0.0.3.1.dist-info/top_level.txt
sitsoDB-0.0.3.1.dist-info/RECORD
