Metadata-Version: 2.1
Name: sitsoDB
Version: 0.0.3.1
Summary: A DataBase Managament Sys, for simple terminal/ GUI projects.
Author: Manasseh Kpormegbe
Author-email: manassekpormegbe@gmail.com
License: MIT
Keywords: database
Classifier: Operating System :: Microsoft :: Windows :: Windows 11
Classifier: Operating System :: Android
Classifier: License :: OSI Approved :: MIT License
Classifier: Programming Language :: Python :: 3
License-File: LICENSE
Requires-Dist: pandas
Requires-Dist: twine
